heliolinx/__init__.py
heliolinx/_version.py
heliolinx/demo.ipynb
heliolinx/heliolinx.cpython-312-x86_64-linux-gnu.so
heliolinx/solarsyst_dyn_geo.py
src/Makefile
src/heliolinc_kd.cpp
src/heliolinx.cpp
src/link_planarity.cpp
src/link_purify.cpp
src/make_tracklets_new.cpp
src/parse_clust2det_MPC80.cpp
src/parse_clust2det_new.cpp
src/solarsyst_dyn_geo01.cpp
src/solarsyst_dyn_geo01.h
heliolinx-0.0.2.dist-info/LICENSE
heliolinx-0.0.2.dist-info/METADATA
heliolinx-0.0.2.dist-info/WHEEL
heliolinx-0.0.2.dist-info/top_level.txt
heliolinx-0.0.2.dist-info/RECORD
heliolinx.libs/libgomp-cd7b8dad.so.1.0.0
