Metadata-Version: 2.1
Name: heliolinx
Version: 0.0.2
Summary: heliolinx: the fast asteroid linking code.
Author-email: Aren Heinze <aheinze@uw.edu>, Mario Juric <mjuric@astro.washington.edu>, Siegfried Eggl <eggls@uw.edu>
License: BSD 3-Clause License
Classifier: Development Status :: 4 - Beta
Classifier: License :: OSI Approved :: BSD License
Classifier: Intended Audience :: Developers
Classifier: Intended Audience :: Science/Research
Classifier: Operating System :: OS Independent
Classifier: Programming Language :: Python
Requires-Python: >=3.9
License-File: LICENSE
Requires-Dist: numpy
Requires-Dist: pybind11 >=2.5.0
